lampsible/__init__.py
lampsible/arg_validator.py
lampsible/cli.py
lampsible/constants.py
lampsible/helpers.py
lampsible/lampsible.py
lampsible/project/ansible-galaxy-requirements.yml
lampsible/project/apache.yml
lampsible/project/drupal.yml
lampsible/project/joomla.yml
lampsible/project/lamp-stack.yml
lampsible/project/laravel.yml
lampsible/project/mysql.yml
lampsible/project/php.yml
lampsible/project/suitecrm.yml
lampsible/project/wordpress.yml
lampsible/project/roles/apache-conf/tasks/main.yml
lampsible/project/roles/apache-conf/templates/ssl-params.conf.j2
lampsible/project/roles/apache-vhosts/tasks/main.yml
lampsible/project/roles/apache-vhosts/templates/000-default.conf.j2
lampsible/project/roles/apache-vhosts/templates/default-ssl.conf.j2
lampsible/project/roles/apache2/tasks/main.yml
lampsible/project/roles/apt/tasks/main.yaml
lampsible/project/roles/composer/tasks/main.yml
lampsible/project/roles/drupal/tasks/main.yml
lampsible/project/roles/fail2ban/tasks/main.yml
lampsible/project/roles/fail2ban/templates/jail.local.j2
lampsible/project/roles/joomla/tasks/main.yml
lampsible/project/roles/laravel/tasks/main.yml
lampsible/project/roles/laravel/templates/.env.j2
lampsible/project/roles/mysql/tasks/main.yml
lampsible/project/roles/mysql/templates/.my.cnf.j2
lampsible/project/roles/phpmyadmin/tasks/main.yml
lampsible/project/roles/pip/tasks/main.yml
lampsible/project/roles/ssl-certbot/tasks/main.yml
lampsible/project/roles/ssl-selfsigned/tasks/main.yml
lampsible/project/roles/suitecrm/tasks/main.yml
lampsible/project/roles/wordpress/tasks/main.yml
lampsible/project/roles/wordpress-block-xmlrpc/tasks/main.yml
lampsible/project/roles/wordpress-block-xmlrpc/templates/.htaccess
lampsible/project/vars/php/main.yml
lampsible-2.5.2.dist-info/licenses/LICENSE
lampsible-2.5.2.dist-info/METADATA
lampsible-2.5.2.dist-info/WHEEL
lampsible-2.5.2.dist-info/entry_points.txt
lampsible-2.5.2.dist-info/top_level.txt
lampsible-2.5.2.dist-info/RECORD
