Metadata-Version: 2.4
Name: lampsible
Version: 2.5.2
Summary: Deploy and set up LAMP stacks with Ansible
Author-email: Belal Ibrahim <belal.ibrahim@proton.me>
Project-URL: Homepage, https://github.com/belal-i/lampsible
Project-URL: Issues, https://github.com/belal-i/lampsible/issues
Classifier: Development Status :: 5 - Production/Stable
Classifier: Environment :: Console
Classifier: Framework :: Ansible
Classifier: Programming Language :: Python :: 3
Classifier: Intended Audience :: Developers
Classifier: Intended Audience :: Information Technology
Classifier: Intended Audience :: System Administrators
Classifier: License :: OSI Approved :: Apache Software License
Requires-Python: >=3.9
License-File: LICENSE
Requires-Dist: ansible-core>=2.15.13
Requires-Dist: ansible-runner>=2.4.1
Requires-Dist: requests>=2.32.3
Requires-Dist: fqdn>=1.5.1
Dynamic: license-file
